[
    {
        "name": "nativescript-barcodescanner",
        "directory": "../../node_modules/nativescript-barcodescanner"
    },
    {
        "name": "nativescript-directions",
        "directory": "../../node_modules/nativescript-directions"
    },
    {
        "name": "nativescript-fonticon",
        "directory": "../../node_modules/nativescript-fonticon"
    },
    {
        "name": "nativescript-geolocation",
        "directory": "../../node_modules/nativescript-geolocation"
    },
    {
        "name": "nativescript-phone",
        "directory": "../../node_modules/nativescript-phone"
    },
    {
        "name": "nativescript-socket.io",
        "directory": "../../node_modules/nativescript-socket.io"
    },
    {
        "name": "nativescript-socketio",
        "directory": "../../node_modules/nativescript-socketio"
    },
    {
        "name": "nativescript-theme-core",
        "directory": "../../node_modules/nativescript-theme-core"
    },
    {
        "name": "nativescript-toast",
        "directory": "../../node_modules/nativescript-toast"
    },
    {
        "name": "nativescript-toasts",
        "directory": "../../node_modules/nativescript-toasts"
    },
    {
        "name": "nativescript-toasty",
        "directory": "../../node_modules/nativescript-toasty"
    },
    {
        "name": "nativescript-ui-listview",
        "directory": "../../node_modules/nativescript-ui-listview"
    },
    {
        "name": "nativescript-vue",
        "directory": "../../node_modules/nativescript-vue"
    },
    {
        "name": "tns-core-modules",
        "directory": "../../node_modules/tns-core-modules"
    },
    {
        "name": "nativescript-appavailability",
        "directory": "../../node_modules/nativescript-appavailability"
    },
    {
        "name": "nativescript-permissions",
        "directory": "../../node_modules/nativescript-permissions"
    },
    {
        "name": "nativescript-ui-core",
        "directory": "../../node_modules/nativescript-ui-core"
    },
    {
        "name": "tns-core-modules-widgets",
        "directory": "../../node_modules/tns-core-modules-widgets"
    }
]